dash_api/__init__.py
dash_api/api_client.py
dash_api/configuration.py
dash_api/rest.py
dash_api/api/__init__.py
dash_api/api/activities_api.py
dash_api/api/charge_api.py
dash_api/api/environment_api.py
dash_api/api/event_api.py
dash_api/api/event_status_api.py
dash_api/api/event_type_api.py
dash_api/api/organisation_api.py
dash_api/api/organisation_type_api.py
dash_api/api/resource_api.py
dash_api/api/restrictions_api.py
dash_api/api/roles_api.py
dash_api/api/teams_api.py
dash_api/api/user_api.py
dash_api/models/__init__.py
dash_api/models/activity.py
dash_api/models/activity_type.py
dash_api/models/address.py
dash_api/models/charge.py
dash_api/models/event.py
dash_api/models/event_status.py
dash_api/models/event_type.py
dash_api/models/organisation.py
dash_api/models/organisation_contact.py
dash_api/models/organisation_group.py
dash_api/models/organisation_type.py
dash_api/models/permission.py
dash_api/models/primary_affiliate_organisation.py
dash_api/models/resource.py
dash_api/models/resource_type.py
dash_api/models/restriction.py
dash_api/models/role.py
dash_api/models/team.py
dash_api/models/user.py
dash_api/models/user_address.py
dash_api_python_client-0.1.0.dist-info/METADATA
dash_api_python_client-0.1.0.dist-info/RECORD
dash_api_python_client-0.1.0.dist-info/WHEEL
dash_api_python_client-0.1.0.dist-info/top_level.txt
test/__init__.py
test/test_activities_api.py
test/test_activity.py
test/test_activity_type.py
test/test_address.py
test/test_charge.py
test/test_charge_api.py
test/test_environment_api.py
test/test_event.py
test/test_event_api.py
test/test_event_status.py
test/test_event_status_api.py
test/test_event_type.py
test/test_event_type_api.py
test/test_organisation.py
test/test_organisation_api.py
test/test_organisation_contact.py
test/test_organisation_group.py
test/test_organisation_type.py
test/test_organisation_type_api.py
test/test_permission.py
test/test_primary_affiliate_organisation.py
test/test_resource.py
test/test_resource_api.py
test/test_resource_type.py
test/test_restriction.py
test/test_restrictions_api.py
test/test_role.py
test/test_roles_api.py
